fastword/__init__.py
fastword/crypto.py
fastword/db.py
fastword/gui.py
fastword/main.py
fastword/utils.py
fastword/wordlist.txt
fastword/icons/__init__.py
fastword/icons/back.svg
fastword/icons/copy.svg
fastword/icons/eye-off.svg
fastword/icons/eye.svg
fastword/icons/pencil.svg
fastword/icons/settings.svg
fastword/icons/trash.svg
fastword-0.2.1.dist-info/licenses/LICENSE
fastword-0.2.1.dist-info/METADATA
fastword-0.2.1.dist-info/WHEEL
fastword-0.2.1.dist-info/entry_points.txt
fastword-0.2.1.dist-info/top_level.txt
fastword-0.2.1.dist-info/RECORD
