Metadata-Version: 2.4
Name: fastword
Version: 0.2.1
Summary: A secure local password manager with PyQt6
Author: Nolan Coe
License: MIT License
License-File: LICENSE
Requires-Dist: PyQt6
Requires-Dist: cryptography
Requires-Dist: argon2-cffi
Dynamic: license-file
